h5io/__init__.py
h5io/_h5io.py
h5io/_version.py
h5io/tests/__init__.py
h5io/tests/test_io.py
h5io-0.2.3.dist-info/LICENSE.txt
h5io-0.2.3.dist-info/METADATA
h5io-0.2.3.dist-info/WHEEL
h5io-0.2.3.dist-info/top_level.txt
h5io-0.2.3.dist-info/RECORD
