Metadata-Version: 2.1
Name: h5io
Version: 0.2.3
Summary: Python Objects Onto HDF5
Home-page: http://h5io.github.io
Download-URL: http://github.com/h5io/h5io
Maintainer: Eric Larson
Maintainer-email: larson.eric.d@gmail.com
License: BSD (3-clause)
Platform: any
Classifier: Intended Audience :: Science/Research
Classifier: Intended Audience :: Developers
Classifier: License :: OSI Approved
Classifier: Programming Language :: Python
Classifier: Topic :: Software Development
Classifier: Topic :: Scientific/Engineering
Classifier: Operating System :: Microsoft :: Windows
Classifier: Operating System :: POSIX
Classifier: Operating System :: Unix
Classifier: Operating System :: MacOS
Requires-Python: >=3.7
License-File: LICENSE.txt
Requires-Dist: numpy
Requires-Dist: h5py
